kjst_kuku/__init__.py
kjst_kuku/main.py
kjst_kuku/stopwatch.py
kjst_kuku/util.py
kjst_kuku-0.1.3.dist-info/entry_points.txt
kjst_kuku-0.1.3.dist-info/WHEEL
kjst_kuku-0.1.3.dist-info/METADATA
kjst_kuku-0.1.3.dist-info/RECORD
