Metadata-Version: 2.1
Name: kjst-kuku
Version: 0.1.3
Summary: 
Author: Kenji Sato
Author-email: mail@kenjisato.jp
Requires-Python: >=3.8,<4.0
Classifier: Programming Language :: Python :: 3
Classifier: Programming Language :: Python :: 3.10
Classifier: Programming Language :: Python :: 3.8
Classifier: Programming Language :: Python :: 3.9
Requires-Dist: pandas (>=1.4.1,<2.0.0)
Requires-Dist: plotly (>=5.6.0,<6.0.0)
Requires-Dist: typer (>=0.4.0,<0.5.0)
